made/__init__.py
made/can.py
made/manifolds.py
made/metrics.py
made/qan.py
made/utils.py
made/visuals.py
ManifoldAttractors-0.0.1.dist-info/LICENSE
ManifoldAttractors-0.0.1.dist-info/METADATA
ManifoldAttractors-0.0.1.dist-info/WHEEL
ManifoldAttractors-0.0.1.dist-info/top_level.txt
ManifoldAttractors-0.0.1.dist-info/RECORD
